lterm-0.1.dist-info/top_level.txt
lterm-0.1.dist-info/DESCRIPTION.rst
lterm-0.1.dist-info/RECORD
lterm-0.1.dist-info/metadata.json
lterm-0.1.dist-info/METADATA
lterm-0.1.dist-info/WHEEL
lterm/__init__.py
lterm/lterm.py
lterm-0.1.data/scripts/lterm.py
