Metadata-Version: 2.0
Name: lterm
Version: 0.1
Summary: lterm is a small script built to install a bash hook for full terminal logging.
Home-page: http://github.com/killswitch-GUI/lterm
Author: Alexander Rymdeko-Harvey
Author-email: lolyearight@cybersyndicates.com
License: GNU 3.0
Platform: UNKNOWN
Requires-Dist: argparse
